{
  "type": "FeatureCollection", 
  "features": [
    {
      "geometry": {
        "type": "Polygon", 
        "coordinates": [
          [
            [
              46.43089156048973, 
              41.89044158926001
            ], 
            [
              46.3927543538349, 
              41.831685486145204
            ], 
            [
              46.37130863419105, 
              41.80569224033877
            ], 
            [
              46.328313843016986, 
              41.7664181521433
            ], 
            [
              46.31374108855994, 
              41.75665130626237
            ], 
            [
              46.297773071048084, 
              41.75081186983056
            ], 
            [
              46.27694746901693, 
              41.749313253090776
            ], 
            [
              46.23012862117935, 
              41.75732309981825
            ], 
            [
              46.20832116723557, 
              41.755514424721724
            ], 
            [
              46.188994181044905, 
              41.74014068640139
            ], 
            [
              46.179537394420095, 
              41.70587921145386
            ], 
            [
              46.180002482404745, 
              41.6551587934878
            ], 
            [
              46.19276656086595, 
              41.61017445916795
            ], 
            [
              46.21968998174253, 
              41.59330210410775
            ], 
            [
              46.22847497571081, 
              41.59872812939736
            ], 
            [
              46.23343591301568, 
              41.607952372929105
            ], 
            [
              46.2400504966883, 
              41.61549713167196
            ], 
            [
              46.25389978074696, 
              41.61591054281425
            ], 
            [
              46.25617354292888, 
              41.610329488796026
            ], 
            [
              46.27839440891427, 
              41.57839345287286
            ], 
            [
              46.287851196438396, 
              41.53214304670493
            ], 
            [
              46.29673954229304, 
              41.51038726870431
            ], 
            [
              46.3139477950304, 
              41.49374745673717
            ], 
            [
              46.366244344100664, 
              41.46656565344699
            ], 
            [
              46.37792321786367, 
              41.462483215269174
            ], 
            [
              46.398283731910055, 
              41.45871083634751
            ], 
            [
              46.44510257974764, 
              41.42594797813976
            ], 
            [
              46.54246097840138, 
              41.39499379502854
            ], 
            [
              46.59155358932014, 
              41.37292795867114
            ], 
            [
              46.60736657720406, 
              41.34502268498264
            ], 
            [
              46.622869506731206, 
              41.34962188708829
            ], 
            [
              46.63103438308673, 
              41.34553944980985
            ], 
            [
              46.63775231954497, 
              41.33696116141272
            ], 
            [
              46.65707930483626, 
              41.32063140870159
            ], 
            [
              46.688498575932215, 
              41.284354553985764
            ], 
            [
              46.69480310034879, 
              41.269781799528744
            ], 
            [
              46.69170251498298, 
              41.26854156520258
            ], 
            [
              46.683434285841884, 
              41.269471741172055
            ], 
            [
              46.67464929187355, 
              41.26166860001564
            ], 
            [
              46.67268558804841, 
              41.253968811644825
            ], 
            [
              46.67160038245083, 
              41.23645050055072
            ], 
            [
              46.66948164899759, 
              41.22988759372046
            ], 
            [
              46.66359053572336, 
              41.223531392461524
            ], 
            [
              46.65036136927739, 
              41.21417795862217
            ], 
            [
              46.6444702560031, 
              41.207976786991225
            ], 
            [
              46.634755086065354, 
              41.18105336521529
            ], 
            [
              46.62948409040382, 
              41.14674021432461
            ], 
            [
              46.6211125084771, 
              41.114597473729674
            ], 
            [
              46.601785522286434, 
              41.094030253212765
            ], 
            [
              46.58214847863843, 
              41.09165313734596
            ], 
            [
              46.56313155080443, 
              41.09558054679499
            ], 
            [
              46.543546183099465, 
              41.09702748669241
            ], 
            [
              46.52241052271165, 
              41.08700225839786
            ], 
            [
              46.51114506009094, 
              41.070982564942796
            ], 
            [
              46.50556400517337, 
              41.055272928945215
            ], 
            [
              46.496779012104355, 
              41.04483428950837
            ], 
            [
              46.474919881318215, 
              41.04411082000942
            ], 
            [
              46.45698815908179, 
              41.05243072509367
            ], 
            [
              46.4290312094501, 
              41.0809561163949
            ], 
            [
              46.41264977989664, 
              41.0918598429171
            ], 
            [
              46.35311853044033, 
              41.10653595015975
            ], 
            [
              46.33234460435227, 
              41.11588938399902
            ], 
            [
              46.273433471609394, 
              41.156300354634396
            ], 
            [
              46.2443913163803, 
              41.18374053943879
            ], 
            [
              46.22857832849644, 
              41.19541941320179
            ], 
            [
              46.21059493031686, 
              41.20017364493552
            ], 
            [
              46.135405720806034, 
              41.199915263421275
            ], 
            [
              46.11313317887749, 
              41.1960395308146
            ], 
            [
              46.061353393735146, 
              41.170924785034515
            ], 
            [
              46.04161299640219, 
              41.165447082902546
            ], 
            [
              46.017428426591664, 
              41.163793437434066
            ], 
            [
              45.96916263795737, 
              41.16828928675409
            ], 
            [
              45.82074792455967, 
              41.208803609275805
            ], 
            [
              45.75108809402326, 
              41.240998026713186
            ], 
            [
              45.70974694831767, 
              41.2677147420186
            ], 
            [
              45.685872436863804, 
              41.29624013331991
            ], 
            [
              45.70809330284919, 
              41.317117411294134
            ], 
            [
              45.731037638333646, 
              41.3232669069821
            ], 
            [
              45.7453003335346, 
              41.32915802025636
            ], 
            [
              45.744060099208355, 
              41.33535919188731
            ], 
            [
              45.720702351682405, 
              41.34238718670224
            ], 
            [
              45.655590047308465, 
              41.35236073815432
            ], 
            [
              45.511826212858864, 
              41.39458038388625
            ], 
            [
              45.479270060222234, 
              41.417679748998665
            ], 
            [
              45.464800659450134, 
              41.43018544504628
            ], 
            [
              45.45002119942194, 
              41.43220082661324
            ], 
            [
              45.416948282857504, 
              41.42460439102797
            ], 
            [
              45.39679447438226, 
              41.423260803916264
            ], 
            [
              45.3812398680127, 
              41.42558624294054
            ], 
            [
              45.31442224132786, 
              41.45163116469013
            ], 
            [
              45.28171105996256, 
              41.45292307585876
            ], 
            [
              45.249619995310695, 
              41.44449981708968
            ], 
            [
              45.002399943361866, 
              41.29045237283117
            ], 
            [
              44.989997599200535, 
              41.28445790677128
            ], 
            [
              44.967363322072856, 
              41.26900665318732
            ], 
            [
              44.95516768438205, 
              41.262702128770655
            ], 
            [
              44.91723718239899, 
              41.26177195280127
            ], 
            [
              44.82070560692921, 
              41.27334747377864
            ], 
            [
              44.801275268852294, 
              41.25851633780741
            ], 
            [
              44.80954349799339, 
              41.24440867133504
            ], 
            [
              44.84706058793478, 
              41.2307660928476
            ], 
            [
              44.857705932942736, 
              41.21934560149819
            ], 
            [
              44.84778405743384, 
              41.20890696206135
            ], 
            [
              44.821532430113166, 
              41.20621978783785
            ], 
            [
              44.67492639181188, 
              41.20849355091906
            ], 
            [
              44.63312015812153, 
              41.221050923809116
            ], 
            [
              44.61286299686077, 
              41.223117981319234
            ], 
            [
              44.591365600374445, 
              41.215779928147555
            ], 
            [
              44.57844649228514, 
              41.202809143215916
            ], 
            [
              44.56625085459433, 
              41.18694447848958
            ], 
            [
              44.55152307140861, 
              41.17702260387992
            ], 
            [
              44.53100752773423, 
              41.18146677725687
            ], 
            [
              44.52552982560218, 
              41.18906321194288
            ], 
            [
              44.52191247540918, 
              41.19929514580846
            ], 
            [
              44.51664147974765, 
              41.20683990545058
            ], 
            [
              44.50589278195412, 
              41.20658152303699
            ], 
            [
              44.49938155106713, 
              41.202809143215916
            ], 
            [
              44.479227742591775, 
              41.18580759694902
            ], 
            [
              44.45493981909635, 
              41.180484924444926
            ], 
            [
              44.432460571596664, 
              41.18167348282802
            ], 
            [
              44.410601440810524, 
              41.18771962483109
            ], 
            [
              44.35727136208595, 
              41.21216257795459
            ], 
            [
              44.34492069476704, 
              41.21324778265276
            ], 
            [
              44.33308679227531, 
              41.21035390285803
            ], 
            [
              44.32492191591979, 
              41.204824523883616
            ], 
            [
              44.31773889147689, 
              41.1985716763094
            ], 
            [
              44.308488810423114, 
              41.19381744457587
            ], 
            [
              44.28497603326912, 
              41.1908718879387
            ], 
            [
              44.26647587116173, 
              41.19619456044259
            ], 
            [
              44.21810672974186, 
              41.2215676886363
            ], 
            [
              44.19097660329413, 
              41.23004262334854
            ], 
            [
              44.180331258286174, 
              41.229939270562994
            ], 
            [
              44.168445678952025, 
              41.223583069303885
            ], 
            [
              44.16586185751413, 
              41.21614166334669
            ], 
            [
              44.165190063958164, 
              41.20766672773519
            ], 
            [
              44.160074097025415, 
              41.1978998827536
            ], 
            [
              44.14436446102775, 
              41.186065979362525
            ], 
            [
              44.12472741737969, 
              41.17805613263505
            ], 
            [
              44.10364343293497, 
              41.17516225194103
            ], 
            [
              44.06126875847434, 
              41.184153951480454
            ], 
            [
              44.04132165557024, 
              41.18255198195516
            ], 
            [
              44.00111739140527, 
              41.168857727524454
            ], 
            [
              43.95584883625065, 
              41.16048614559776
            ], 
            [
              43.86324466933053, 
              41.15898752885798
            ], 
            [
              43.82035323094209, 
              41.14549997999845
            ], 
            [
              43.77374108867565, 
              41.11449412094407
            ], 
            [
              43.75415572097069, 
              41.10824127247065
            ], 
            [
              43.72971276874648, 
              41.106690978888366
            ], 
            [
              43.56662194810616, 
              41.124054260354484
            ], 
            [
              43.524143920859956, 
              41.12281402602832
            ], 
            [
              43.47014204947885, 
              41.10617421496053
            ], 
            [
              43.460323526755474, 
              41.10452056949205
            ], 
            [
              43.450453328089, 
              41.10467559822075
            ], 
            [
              43.440428100693794, 
              41.10658762610282
            ], 
            [
              43.451796916100136, 
              41.132580871909255
            ], 
            [
              43.43758589684222, 
              41.156197001848795
            ], 
            [
              43.410559123180064, 
              41.17516225194103
            ], 
            [
              43.383273966205024, 
              41.18720286090317
            ], 
            [
              43.351751343222816, 
              41.193610738105264
            ], 
            [
              43.32260583520815, 
              41.19206044542241
            ], 
            [
              43.23062178590084, 
              41.172630107345526
            ], 
            [
              43.21620406107178, 
              41.18053660128746
            ], 
            [
              43.192226195933074, 
              41.22497833325815
            ], 
            [
              43.17202071151462, 
              41.242341613824976
            ], 
            [
              43.15233199102414, 
              41.24415028892153
            ], 
            [
              43.1303178306099, 
              41.24228993788182
            ], 
            [
              43.10313602731975, 
              41.248801167869544
            ], 
            [
              43.15724125148648, 
              41.26973012358556
            ], 
            [
              43.17186568188663, 
              41.27934193983853
            ], 
            [
              43.1853532307461, 
              41.29381134061066
            ], 
            [
              43.18400964363434, 
              41.29897898348659
            ], 
            [
              43.1547607828341, 
              41.30187286418058
            ], 
            [
              43.12390995250843, 
              41.3129316203308
            ], 
            [
              43.075644164773564, 
              41.34486765535465
            ], 
            [
              43.002056925687384, 
              41.382694804552074
            ], 
            [
              42.98758752401602, 
              41.394683736671766
            ], 
            [
              42.95771854650229, 
              41.43700673429004
            ], 
            [
              42.949967081289, 
              41.44367299390572
            ], 
            [
              42.94107873543447, 
              41.44630849218615
            ], 
            [
              42.93622115091523, 
              41.45023590163527
            ], 
            [
              42.93219038868057, 
              41.45478342689847
            ], 
            [
              42.926092569835134, 
              41.45907257154661
            ], 
            [
              42.896637003463695, 
              41.46656565344699
            ], 
            [
              42.888988891935355, 
              41.46997629806884
            ], 
            [
              42.88072066279426, 
              41.48124176068956
            ], 
            [
              42.87513960787669, 
              41.493695780793985
            ], 
            [
              42.86800826027627, 
              41.50020701078179
            ], 
            [
              42.854572387359894, 
              41.493799133579614
            ], 
            [
              42.8299744055077, 
              41.472508443563726
            ], 
            [
              42.81116418504348, 
              41.477159322511824
            ], 
            [
              42.792147257209535, 
              41.49286895761011
            ], 
            [
              42.766515747501614, 
              41.50434112580197
            ], 
            [
              42.77488732942828, 
              41.5142630004116
            ], 
            [
              42.79462772586197, 
              41.52682037420095
            ], 
            [
              42.80268924943192, 
              41.5341067505301
            ], 
            [
              42.8068233644521, 
              41.54299509728398
            ], 
            [
              42.808890421962246, 
              41.55291697189364
            ], 
            [
              42.81219771289926, 
              41.56299387613126
            ], 
            [
              42.819949178112495, 
              41.572347310869816
            ], 
            [
              42.80093225117781, 
              41.57922027605673
            ], 
            [
              42.660992472492296, 
              41.588263651539336
            ], 
            [
              42.610556274461715, 
              41.585059713387835
            ], 
            [
              42.58523482221119, 
              41.578755188071995
            ], 
            [
              42.56518436652158, 
              41.56712799115144
            ], 
            [
              42.55495243355517, 
              41.55033315045566
            ], 
            [
              42.54554732287346, 
              41.509612121463505
            ], 
            [
              42.535522094578994, 
              41.49348907522284
            ], 
            [
              42.51381799342073, 
              41.47622914654232
            ], 
            [
              42.483845662222166, 
              41.44217437806523
            ], 
            [
              42.46307173703349, 
              41.43183909141402
            ], 
            [
              42.43785363756848, 
              41.43085723950145
            ], 
            [
              42.26246382645172, 
              41.482326965387756
            ], 
            [
              42.21326786274733, 
              41.48020823193454
            ], 
            [
              42.18928999850789, 
              41.48170684867429
            ], 
            [
              42.17265018744007, 
              41.49348907522284
            ], 
            [
              42.158387492239115, 
              41.49989695242502
            ], 
            [
              42.143194621068744, 
              41.500258687624154
            ], 
            [
              42.11177534997279, 
              41.49348907522284
            ], 
            [
              42.09751265477172, 
              41.49834665974208
            ], 
            [
              42.08345666514191, 
              41.50010365799616
            ], 
            [
              42.069400675512156, 
              41.498605042155674
            ], 
            [
              42.05493127473994, 
              41.49348907522284
            ], 
            [
              42.01958459509433, 
              41.48506581645378
            ], 
            [
              41.94796105983335, 
              41.50558136012813
            ], 
            [
              41.90775679566843, 
              41.49348907522284
            ], 
            [
              41.89401086439534, 
              41.485530904438434
            ], 
            [
              41.8626949460849, 
              41.45178619431812
            ], 
            [
              41.82259403470556, 
              41.425999654082915
            ], 
            [
              41.8129822184527, 
              41.42181386311947
            ], 
            [
              41.80078658076184, 
              41.42568959572614
            ], 
            [
              41.76099572773916, 
              41.4535431925722
            ], 
            [
              41.74776656129325, 
              41.456850484408506
            ], 
            [
              41.71851770049295, 
              41.45958933547453
            ], 
            [
              41.70683882672995, 
              41.46315500882508
            ], 
            [
              41.70260135892414, 
              41.46945953414101
            ], 
            [
              41.70280806449529, 
              41.477624410496475
            ], 
            [
              41.70394494603602, 
              41.48511749329623
            ], 
            [
              41.70260135892414, 
              41.48904490184597
            ], 
            [
              41.69495324739586, 
              41.48909657868833
            ], 
            [
              41.66983850071648, 
              41.48046661434813
            ], 
            [
              41.63996952320275, 
              41.47870961519476
            ], 
            [
              41.6272571206847, 
              41.4805182902912
            ], 
            [
              41.521320434533095, 
              41.5140046188973
            ], 
            [
              41.58684615094859, 
              41.60252634674032
            ], 
            [
              41.61609501174888, 
              41.63234364831089
            ], 
            [
              41.67655643717461, 
              41.661954244310294
            ], 
            [
              41.69340295381363, 
              41.692029928294545
            ], 
            [
              41.74032515443673, 
              41.749674988289996
            ], 
            [
              41.74280562308917, 
              41.76143137641725
            ], 
            [
              41.743012329559576, 
              41.77039723753552
            ], 
            [
              41.744355916671395, 
              41.778407084262994
            ], 
            [
              41.750557088302344, 
              41.787243754174455
            ], 
            [
              41.76678348822793, 
              41.80393524208469
            ], 
            [
              41.77226118946061, 
              41.81235850085383
            ], 
            [
              41.77443159975627, 
              41.82137603791517
            ], 
            [
              41.77443159975627, 
              41.90671966602795
            ], 
            [
              41.76254602042212, 
              41.96960988416302
            ], 
            [
              41.7606856693825, 
              41.99234751407624
            ], 
            [
              41.756138143219914, 
              42.00617095971373
            ], 
            [
              41.68544478392852, 
              42.098671773848224
            ], 
            [
              41.674799438920616, 
              42.10533803346394
            ], 
            [
              41.66456750505495, 
              42.11370961539063
            ], 
            [
              41.65960656775013, 
              42.132778219167676
            ], 
            [
              41.65764286302556, 
              42.1668071492235
            ], 
            [
              41.64968469224124, 
              42.21199819001387
            ], 
            [
              41.59676802555816, 
              42.34919911763336
            ], 
            [
              41.59294396979402, 
              42.355167745271984
            ], 
            [
              41.58570926940797, 
              42.36260915122918
            ], 
            [
              41.55894087726011, 
              42.38255625413328
            ], 
            [
              41.55522017428149, 
              42.38958424894818
            ], 
            [
              41.50064986123067, 
              42.640344136725645
            ], 
            [
              41.4832865806639, 
              42.679979960120335
            ], 
            [
              41.45786177562775, 
              42.71346628872641
            ], 
            [
              41.42478885906331, 
              42.73961456326154
            ], 
            [
              41.38406783007116, 
              42.757029520670756
            ], 
            [
              41.30779341676151, 
              42.7674681601076
            ], 
            [
              41.29146366405041, 
              42.77410858220139
            ], 
            [
              41.275443969696084, 
              42.784986471201705
            ], 
            [
              41.251259399885555, 
              42.79501169859688
            ], 
            [
              41.2258345948494, 
              42.802039693411785
            ], 
            [
              41.205887491945305, 
              42.80423594212871
            ], 
            [
              41.1942086181823, 
              42.80157460542705
            ], 
            [
              41.17405480970706, 
              42.792531229944444
            ], 
            [
              41.16144575997453, 
              42.79056752521993
            ], 
            [
              41.15080041496657, 
              42.79542510973917
            ], 
            [
              41.10532515424086, 
              42.84632639575449
            ], 
            [
              41.08227746597089, 
              42.907873026777764
            ], 
            [
              41.04083296747979, 
              42.96107391429564
            ], 
            [
              41.02346968601364, 
              42.989754333426276
            ], 
            [
              40.99897505694696, 
              42.989185892655996
            ], 
            [
              40.959494262281, 
              42.9761375942592
            ], 
            [
              40.93427616371537, 
              42.9825196330402
            ], 
            [
              40.904510538987324, 
              43.016109314431844
            ], 
            [
              40.88714725752112, 
              43.02393829400944
            ], 
            [
              40.88663049359326, 
              43.029054260942274
            ], 
            [
              40.86327274606725, 
              43.05866485604233
            ], 
            [
              40.85645145682349, 
              43.06282480948377
            ], 
            [
              40.783587687236434, 
              43.08383127866489
            ], 
            [
              40.68343876157354, 
              43.09401153568814
            ], 
            [
              40.63672326652153, 
              43.092228699012765
            ], 
            [
              40.60447717314105, 
              43.086234232952876
            ], 
            [
              40.592281534550864, 
              43.085407409769005
            ], 
            [
              40.58049930800223, 
              43.088585510398616
            ], 
            [
              40.561068969925316, 
              43.102667338449606
            ], 
            [
              40.55104374163079, 
              43.1058971150222
            ], 
            [
              40.54649621546838, 
              43.108584290145075
            ], 
            [
              40.5293396404727, 
              43.122046000583424
            ], 
            [
              40.52055464650431, 
              43.126981099466946
            ], 
            [
              40.510632771894734, 
              43.12971995053297
            ], 
            [
              40.47900679522763, 
              43.133802388710706
            ], 
            [
              40.398804972468895, 
              43.16209523512032
            ], 
            [
              40.361701293669796, 
              43.16524749822793
            ], 
            [
              40.33565637192032, 
              43.14064951637573
            ], 
            [
              40.32563114452506, 
              43.148530171896425
            ], 
            [
              40.31085168449698, 
              43.17547943119425
            ], 
            [
              40.301446573815156, 
              43.18837270176152
            ], 
            [
              40.27881229668748, 
              43.20529673276491
            ], 
            [
              40.26899377486353, 
              43.21609710740077
            ], 
            [
              40.27333459455559, 
              43.24772308406787
            ], 
            [
              40.25762495945719, 
              43.27717865043931
            ], 
            [
              40.23571415182852, 
              43.3042054241015
            ], 
            [
              40.219591105587995, 
              43.31877817855852
            ], 
            [
              40.1886885984199, 
              43.32937184672397
            ], 
            [
              40.13391158069726, 
              43.34133494132183
            ], 
            [
              40.101768839202975, 
              43.36489939441893
            ], 
            [
              40.08729943843082, 
              43.3700153604525
            ], 
            [
              40.04130741377713, 
              43.37551890100565
            ], 
            [
              40.01030155472279, 
              43.38489817326618
            ], 
            [
              39.985910278441736, 
              43.38877390587285
            ], 
            [
              39.9912846268889, 
              43.40631805448888
            ], 
            [
              40.0591874591712, 
              43.53519907702412
            ], 
            [
              40.07283003765872, 
              43.551063741750454
            ], 
            [
              40.09670454911259, 
              43.562639261828565
            ], 
            [
              40.16429732303811, 
              43.575842590752615
            ], 
            [
              40.23313033039062, 
              43.57576507638828
            ], 
            [
              40.47983361841153, 
              43.508740743233005
            ], 
            [
              40.51962447143421, 
              43.5051750698824
            ], 
            [
              40.55083703605965, 
              43.51124705030654
            ], 
            [
              40.61553592929124, 
              43.53584503215873
            ], 
            [
              40.65191613769207, 
              43.53897145594587
            ], 
            [
              40.681061645706734, 
              43.52806772942367
            ], 
            [
              40.74017948402076, 
              43.495279032794656
            ], 
            [
              40.84270552555046, 
              43.469389139773824
            ], 
            [
              40.874951619830256, 
              43.45564320940005
            ], 
            [
              41.01179081225064, 
              43.375415548220104
            ], 
            [
              41.04248661294821, 
              43.369834493302534
            ], 
            [
              41.146666300845766, 
              43.37985972159706
            ], 
            [
              41.18077274616519, 
              43.37469207782178
            ], 
            [
              41.213122192331355, 
              43.36278066006642
            ], 
            [
              41.2439213458145, 
              43.34420298269529
            ], 
            [
              41.27875126153236, 
              43.3331959024882
            ], 
            [
              41.350271444007774, 
              43.34335032198953
            ], 
            [
              41.38065718544925, 
              43.334772033592316
            ], 
            [
              41.3897522377743, 
              43.32487599740395
            ], 
            [
              41.40380822740411, 
              43.301518249877915
            ], 
            [
              41.41310998530031, 
              43.291286316012304
            ], 
            [
              41.42757938607241, 
              43.28319895492038
            ], 
            [
              41.47977258325636, 
              43.271235860322605
            ], 
            [
              41.506127563362725, 
              43.25978953055201
            ], 
            [
              41.55056929533339, 
              43.22627736442402
            ], 
            [
              41.57754439305239, 
              43.21529612263808
            ], 
            [
              41.614131307024365, 
              43.2130223595569
            ], 
            [
              41.68740848775377, 
              43.22020538399977
            ], 
            [
              41.723788696154486, 
              43.217233988941416
            ], 
            [
              41.78890100142769, 
              43.203565572032716
            ], 
            [
              41.82032027162427, 
              43.201240133008355
            ], 
            [
              41.88998010216068, 
              43.20702789349701
            ], 
            [
              41.91933231574649, 
              43.20594268789952
            ], 
            [
              41.94827111819012, 
              43.200077413046444
            ], 
            [
              41.97969038928608, 
              43.18865692169703
            ], 
            [
              42.01131636595318, 
              43.18186147087454
            ], 
            [
              42.04335575376257, 
              43.180569559705816
            ], 
            [
              42.075291788786444, 
              43.18527211549636
            ], 
            [
              42.15983443213645, 
              43.21974029601503
            ], 
            [
              42.18536258995812, 
              43.22547637966133
            ], 
            [
              42.354551228544665, 
              43.23601837188369
            ], 
            [
              42.422867471969255, 
              43.22899037706878
            ], 
            [
              42.47971154810125, 
              43.2009042362304
            ], 
            [
              42.506066528207555, 
              43.18155141251776
            ], 
            [
              42.53490197786556, 
              43.16506663017867
            ], 
            [
              42.59588016811847, 
              43.140029398763005
            ], 
            [
              42.61520715340981, 
              43.13698048934029
            ], 
            [
              42.629366495825195, 
              43.141269633089166
            ], 
            [
              42.65623824075868, 
              43.15979563451714
            ], 
            [
              42.67360152222483, 
              43.16589345336254
            ], 
            [
              42.704917439635835, 
              43.16643605571164
            ], 
            [
              42.751529581902275, 
              43.17695220951285
            ], 
            [
              42.791320434924955, 
              43.17617706317131
            ], 
            [
              42.82976769993655, 
              43.16876149563538
            ], 
            [
              42.85767297362503, 
              43.155454813925815
            ], 
            [
              42.88578495288465, 
              43.13584360779956
            ], 
            [
              42.91482710811374, 
              43.12194264779782
            ], 
            [
              43.00009322096287, 
              43.09866241463624
            ], 
            [
              43.0001965737485, 
              43.085355733825935
            ], 
            [
              42.99254846222016, 
              43.06881927554366
            ], 
            [
              42.98975793431168, 
              43.052670389982524
            ], 
            [
              42.998852986636734, 
              43.04220591302379
            ], 
            [
              43.04825565591227, 
              43.016961975137605
            ], 
            [
              43.155587606018, 
              42.94239288323959
            ], 
            [
              43.19434493028564, 
              42.926760762505666
            ], 
            [
              43.47959883610366, 
              42.86746205704168
            ], 
            [
              43.51742598440177, 
              42.86045990064801
            ], 
            [
              43.5862589926536, 
              42.8356293748034
            ], 
            [
              43.60300215650699, 
              42.824803161746274
            ], 
            [
              43.64434330221252, 
              42.78857798297352
            ], 
            [
              43.66284346521928, 
              42.77984466584769
            ], 
            [
              43.75596439606721, 
              42.76312734041554
            ], 
            [
              43.80061283360914, 
              42.74646169092648
            ], 
            [
              43.81177494344422, 
              42.71726450606937
            ], 
            [
              43.78872725427499, 
              42.693079936258755
            ], 
            [
              43.75379398577155, 
              42.67465728761633
            ], 
            [
              43.72568200651193, 
              42.654400126355455
            ], 
            [
              43.72258142114606, 
              42.624867045619766
            ], 
            [
              43.75110681154797, 
              42.59874460860652
            ], 
            [
              43.79616866023218, 
              42.58983042433073
            ], 
            [
              43.845002888737326, 
              42.58703989732163
            ], 
            [
              43.8853621825304, 
              42.57921091774401
            ], 
            [
              43.920812214961586, 
              42.55910878521195
            ], 
            [
              43.939725789110696, 
              42.55220998160374
            ], 
            [
              43.958432657688604, 
              42.554406230320666
            ], 
            [
              43.9732121177168, 
              42.56399220815237
            ], 
            [
              43.99801680514014, 
              42.58936533634599
            ], 
            [
              44.011504353999555, 
              42.60032073971067
            ], 
            [
              44.055067585944016, 
              42.61530690530998
            ], 
            [
              44.150824015072374, 
              42.61866587308944
            ], 
            [
              44.19738448049634, 
              42.6291045125262
            ], 
            [
              44.230147338704, 
              42.65380584716402
            ], 
            [
              44.248647501710764, 
              42.6819953416873
            ], 
            [
              44.27200524923677, 
              42.70238169415495
            ], 
            [
              44.360682006707805, 
              42.70375111968792
            ], 
            [
              44.40140303569996, 
              42.71351796466951
            ], 
            [
              44.479227742591775, 
              42.74429128063082
            ], 
            [
              44.50811486819293, 
              42.75028574669071
            ], 
            [
              44.558292683809896, 
              42.75310211212101
            ], 
            [
              44.6009774166273, 
              42.749123026728796
            ], 
            [
              44.642421916017724, 
              42.7392786664835
            ], 
            [
              44.67942224113199, 
              42.72367238417084
            ], 
            [
              44.69502852344465, 
              42.71421559664665
            ], 
            [
              44.72448408981609, 
              42.691038717169874
            ], 
            [
              44.736369670049555, 
              42.677551168310345
            ], 
            [
              44.761071004687324, 
              42.61923431385972
            ], 
            [
              44.773473347949334, 
              42.609648336028044
            ], 
            [
              44.782310017860766, 
              42.61665049242177
            ], 
            [
              44.79848474094382, 
              42.67173756940042
            ], 
            [
              44.827423543387454, 
              42.71796213804643
            ], 
            [
              44.83367639186082, 
              42.734085185186416
            ], 
            [
              44.859359578411215, 
              42.75950998932319
            ], 
            [
              44.902974487198094, 
              42.75307627369983
            ], 
            [
              45.01211511240041, 
              42.6953020224976
            ], 
            [
              45.029788452223215, 
              42.6887649540887
            ], 
            [
              45.04808190965883, 
              42.685896911815775
            ], 
            [
              45.06699548380789, 
              42.68845489573184
            ], 
            [
              45.103892456136464, 
              42.70054718063713
            ], 
            [
              45.122961059913564, 
              42.70227834136932
            ], 
            [
              45.155362182922204, 
              42.69326080340872
            ], 
            [
              45.18419763168083, 
              42.67483815566567
            ], 
            [
              45.28269291187513, 
              42.58639394128764
            ], 
            [
              45.29364831523981, 
              42.572906392428166
            ], 
            [
              45.31256188938886, 
              42.54171966622383
            ], 
            [
              45.322690470468956, 
              42.530118306825244
            ], 
            [
              45.35597009260459, 
              42.51996388822329
            ], 
            [
              45.39855147263637, 
              42.524382223178975
            ], 
            [
              45.479270060222234, 
              42.54233978293726
            ], 
            [
              45.53683760585335, 
              42.54135793102469
            ], 
            [
              45.620656778805085, 
              42.53037668923875
            ], 
            [
              45.69868819216748, 
              42.50758738248311
            ], 
            [
              45.7396159258314, 
              42.471465556495986
            ], 
            [
              45.73641198768007, 
              42.44753936819967
            ], 
            [
              45.62138024920341, 
              42.22447804764022
            ], 
            [
              45.631405476598616, 
              42.20117197695663
            ], 
            [
              45.66158451336838, 
              42.1867025761845
            ], 
            [
              45.70178877753335, 
              42.17274993934021
            ], 
            [
              45.81160119629152, 
              42.115492452065894
            ], 
            [
              45.881364379613444, 
              42.10203074162763
            ], 
            [
              45.895161987728955, 
              42.091876323025645
            ], 
            [
              45.92348067255983, 
              42.039631449898565
            ], 
            [
              45.934126017567735, 
              42.02849517848463
            ], 
            [
              45.94756188958485, 
              42.02291412356706
            ], 
            [
              45.96637211094827, 
              42.022061462861274
            ], 
            [
              45.973503458548805, 
              42.02415435789331
            ], 
            [
              45.98673262499466, 
              42.03190582310657
            ], 
            [
              45.9951558837638, 
              42.03345611578942
            ], 
            [
              46.00161543780837, 
              42.03097564713707
            ], 
            [
              46.01835860166176, 
              42.0200460821936
            ], 
            [
              46.026730183588484, 
              42.016790466300364
            ], 
            [
              46.04481693545296, 
              42.017720642269865
            ], 
            [
              46.058459513041214, 
              42.02033030212908
            ], 
            [
              46.068278035764536, 
              42.01531768798185
            ], 
            [
              46.07499597132335, 
              41.99348439561689
            ], 
            [
              46.09918054203325, 
              41.98506113684772
            ], 
            [
              46.12987634273088, 
              41.98449269607735
            ], 
            [
              46.188580769902615, 
              41.993536072459335
            ], 
            [
              46.18889082825939, 
              41.993639425244936
            ], 
            [
              46.189200887515426, 
              41.99376861645166
            ], 
            [
              46.197675822227666, 
              41.99549977628456
            ], 
            [
              46.206150756939905, 
              41.99609405547611
            ], 
            [
              46.21457401570905, 
              41.99549977628456
            ], 
            [
              46.22434086069063, 
              41.99348439561689
            ], 
            [
              46.25048913612511, 
              41.977723083676125
            ], 
            [
              46.294155720854974, 
              41.93862986263056
            ], 
            [
              46.322629435313786, 
              41.92901804637768
            ], 
            [
              46.38205733198458, 
              41.925245666556634
            ], 
            [
              46.40655196105115, 
              41.9150395711122
            ], 
            [
              46.43089156048973, 
              41.89044158926001
            ]
          ]
        ]
      }, 
      "id": 23424823, 
      "type": "Feature", 
      "properties": {
        "alias_ENG_V": [
          "Georgian Soviet Socialist Republic"
        ], 
        "ne:ne_10m_adm": "GEO", 
        "alias_SWE_Q": [
          "Georgien"
        ], 
        "alias_POL_Q": [
          "Gruzja"
        ], 
        "ne_latitude": 43.575842590752615, 
        "alias_UNK_V": [
          "Sakartvelo"
        ], 
        "placetype": "Country", 
        "alias_KOR_V": [
          "\uadf8\ub8e8\uc9c0\uc544"
        ], 
        "alias_POR_Q": [
          "Ge\u00f3rgia"
        ], 
        "alias_KOR_Q": [
          "\uadf8\ub8e8\uc9c0\uc57c"
        ], 
        "ne:SUBUNIT": "Georgia", 
        "ne:ISO_N3": 268.0, 
        "ne:ADM0_A3": "GEO", 
        "ne:ScaleRank": 1, 
        "alias_CHI_Q": [
          "\u55ac\u6cbb\u4e9e"
        ], 
        "ne:GDP_MD_EST": 21510.0, 
        "ne:NAME": "Georgia", 
        "ne:POSTAL": "GE", 
        "alias_JPN_Q": [
          "\u30b0\u30eb\u30b8\u30a2"
        ], 
        "ne:LEVEL": 2.0, 
        "alias_JPN_V": [
          "\u30b0\u30eb\u30b8\u30a2\u5171\u548c\u56fd"
        ], 
        "ne:FIPS_10_": 0.0, 
        "ne:TERR_": null, 
        "sw_longitude": 39.985910278441736, 
        "ne:SOV_A3": "GEO", 
        "ne:SU_A3": "GEO", 
        "provider": "geoplanet 7.6.0", 
        "latitude": 42.312, 
        "woe:id": 23424823, 
        "ne:OID_": 134, 
        "ne:ISO_A3": "GEO", 
        "ne:ISO_A2": "GE", 
        "date_indexed": "2010-12-02T17:51:59Z", 
        "ne:NAME_FORMA": null, 
        "alias_CHI_V": [
          "\u55ac\u6cbb\u4e9e"
        ], 
        "ne:GU_A3": "GEO", 
        "ne:MAP_COLOR": 2.0, 
        "ne:ADMIN": "Georgia", 
        "ne:GEOUNIT": "Georgia", 
        "ne:LabelRank": 2, 
        "alias_ENG_A": [
          "GE"
        ], 
        "ne:FeatureCla": "Adm-0 country", 
        "ne:ADM0_DIF": 0.0, 
        "alias_DUT_Q": [
          "Georgi\u00eb"
        ], 
        "alias_DUT_S": [
          "Georgie"
        ], 
        "ne:ABBREV": "Geo.", 
        "alias_CZE_Q": [
          "Gruzie"
        ], 
        "alias_DAN_Q": [
          "Georgien"
        ], 
        "alias_GER_Q": [
          "Georgien"
        ], 
        "fullname": "Georgia", 
        "lang": "ENG", 
        "name": "Georgia", 
        "ne:TYPE": "Sovereign country", 
        "parent_woeid": 1, 
        "alias_UNK_Q": [
          "Gruzija"
        ], 
        "alias_HUN_Q": [
          "Gr\u00fazia"
        ], 
        "ne:NAME_SORT": "Georgia", 
        "longitude": 43.366, 
        "ne:POP_EST": 4615807.0, 
        "ne_longitude": 46.69480310034879, 
        "iso": "GE", 
        "sw_latitude": 41.04411082000942, 
        "ne:GEOU_DIF": 0.0, 
        "ne:SU_DIF": 0.0, 
        "ne:SOVEREIGNT": "Georgia", 
        "alias_FRE_S": [
          "Georgie"
        ], 
        "alias_FRE_Q": [
          "G\u00e9orgie"
        ]
      }, 
      "bbox": [
        39.955008579270924, 
        41.06444468847411, 
        46.63790815612058, 
        43.553104153002316
      ]
    }
  ], 
  "bbox": [
    39.985910278441736, 
    41.04411082000942, 
    46.69480310034879, 
    43.575842590752615
  ]
}