{
  "type": "FeatureCollection", 
  "features": [
    {
      "geometry": {
        "type": "MultiPolygon", 
        "coordinates": [
          [
            [
              [
                101.07551557821333, 
                6.204867051615892
              ], 
              [
                101.15421878459384, 
                5.691384182147715
              ], 
              [
                101.81428185425804, 
                5.810808417174229
              ], 
              [
                102.14118696493645, 
                6.221636053894656
              ], 
              [
                102.37114708863524, 
                6.128205064310961
              ], 
              [
                102.9617053568667, 
                5.524495144061078
              ], 
              [
                103.38121463421217, 
                4.855001125503748
              ], 
              [
                103.4385754740562, 
                4.181605536308382
              ], 
              [
                103.33212202353488, 
                3.726697902842972
              ], 
              [
                103.42942874554055, 
                3.38286876058902
              ], 
              [
                103.50244754436889, 
                2.791018581550205
              ], 
              [
                103.85467410687036, 
                2.515454006353764
              ], 
              [
                104.24793175661151, 
                1.631141058759056
              ], 
              [
                104.22881147666354, 
                1.293048000489534
              ], 
              [
                103.51970747275445, 
                1.226333726400682
              ], 
              [
                102.5736153503548, 
                1.967115383304744
              ], 
              [
                101.39063846232918, 
                2.760813706875624
              ], 
              [
                101.27353966675585, 
                3.270291652841181
              ], 
              [
                100.6954354187067, 
                3.93913971599487
              ], 
              [
                100.5574076680551, 
                4.76728038168828
              ], 
              [
                100.19670617065773, 
                5.31249258058368
              ], 
              [
                100.30626020711654, 
                6.040561835143876
              ], 
              [
                100.08575687052709, 
                6.464489447450291
              ], 
              [
                100.25959638875693, 
                6.642824815289572
              ], 
              [
                101.07551557821333, 
                6.204867051615892
              ]
            ]
          ], 
          [
            [
              [
                118.61832075406485, 
                4.478202419447541
              ], 
              [
                117.88203494677018, 
                4.137551377779488
              ], 
              [
                117.01521447150637, 
                4.306094061699469
              ], 
              [
                115.86551720587678, 
                4.306559149590157
              ], 
              [
                115.51907840379201, 
                3.169238389494396
              ], 
              [
                115.13403730678525, 
                2.821481838386219
              ], 
              [
                114.6213554220175, 
                1.430688177898887
              ], 
              [
                113.80584964401956, 
                1.217548732911041
              ], 
              [
                112.8598091980522, 
                1.497790025229946
              ], 
              [
                112.38025190638368, 
                1.410120957846758
              ], 
              [
                111.79754845586044, 
                0.904441229654651
              ], 
              [
                111.15913781132659, 
                0.976478176269509
              ], 
              [
                110.51406090702713, 
                0.773131415200993
              ], 
              [
                109.83022667850886, 
                1.338135687664192
              ], 
              [
                109.66326012577375, 
                2.006466986494985
              ], 
              [
                110.39613528853707, 
                1.663774725751395
              ], 
              [
                111.1688529805975, 
                1.850636704918784
              ], 
              [
                111.3700810079421, 
                2.697303371588873
              ], 
              [
                111.79692833867287, 
                2.885896511238073
              ], 
              [
                112.99561486211527, 
                3.102394924324869
              ], 
              [
                113.71293541875875, 
                3.893509426281128
              ], 
              [
                114.20401655482843, 
                4.52587392823682
              ], 
              [
                114.65959598191355, 
                4.00763682699781
              ], 
              [
                114.8695573263154, 
                4.348313706881953
              ], 
              [
                115.34746097215069, 
                4.316636053887009
              ], 
              [
                115.40570031134362, 
                4.955227565933825
              ], 
              [
                115.45071048386981, 
                5.447729803891562
              ], 
              [
                116.22074100145099, 
                6.143191229675622
              ], 
              [
                116.72510298061977, 
                6.924771429873999
              ], 
              [
                117.12962609260049, 
                6.928052883324568
              ], 
              [
                117.64339318244632, 
                6.422166449403306
              ], 
              [
                117.68907514859237, 
                5.987490139180181
              ], 
              [
                118.34769127815221, 
                5.708695786965464
              ], 
              [
                119.18190392463995, 
                5.407835598162251
              ], 
              [
                119.11069380094173, 
                5.016128241389865
              ], 
              [
                118.43972700406411, 
                4.96651886638962
              ], 
              [
                118.61832075406485, 
                4.478202419447541
              ]
            ]
          ]
        ]
      }, 
      "id": 23424901, 
      "type": "Feature", 
      "properties": {
        "alias_ENG_V": [
          "Malaysian"
        ], 
        "alias_KOR_Q": [
          "\ub9d0\ub808\uc774\uc2dc\uc544"
        ], 
        "alias_POL_Q": [
          "Malezja"
        ], 
        "ne_latitude": 6.928052883324568, 
        "alias_RUM_Q": [
          "Malaezia"
        ], 
        "alias_UNK_V": [
          "Mallae-i jia"
        ], 
        "placetype": "Country", 
        "alias_KOR_V": [
          "\ub9d0\ub808\uc774\uc9c0\uc544"
        ], 
        "alias_POR_Q": [
          "Mal\u00e1sia"
        ], 
        "alias_ENG_A": [
          "MY"
        ], 
        "ne:SUBUNIT": "Malaysia", 
        "ne:ISO_N3": 458.0, 
        "ne:ADM0_A3": "MYS", 
        "ne:ScaleRank": 1, 
        "alias_CHI_Q": [
          "\u99ac\u4f86\u897f\u4e9e"
        ], 
        "alias_ITA_Q": [
          "Malesia"
        ], 
        "alias_ITA_V": [
          "Malaisia"
        ], 
        "ne:POSTAL": "MY", 
        "alias_JPN_Q": [
          "\u30de\u30ec\u30fc\u30b7\u30a2"
        ], 
        "ne:LEVEL": 2.0, 
        "alias_JPN_V": [
          "\u30de\u30ec\u30a4\u30b7\u30a2"
        ], 
        "ne:FIPS_10_": 0.0, 
        "alias_SPA_Q": [
          "Malasia"
        ], 
        "ne:TERR_": null, 
        "sw_longitude": 100.08575687052709, 
        "ne:SOV_A3": "MYS", 
        "alias_FIN_V": [
          "Malesiaan"
        ], 
        "alias_RUM_V": [
          "Malaiezia"
        ], 
        "latitude": 3.945, 
        "woe:id": 23424901, 
        "ne:ISO_A3": "MYS", 
        "ne:ISO_A2": "MY", 
        "date_indexed": "2010-12-02T18:04:56Z", 
        "ne:NAME_FORMA": null, 
        "alias_CHI_V": [
          "\u9a6c\u6765\u897f\u4e9a"
        ], 
        "ne:GU_A3": "MYS", 
        "ne:MAP_COLOR": 6.0, 
        "ne:ADMIN": "Malaysia", 
        "ne:SU_A3": "MYS", 
        "ne:LabelRank": 1, 
        "ne:GDP_MD_EST": 384300.0, 
        "provider": "geoplanet 7.6.0", 
        "wikipedia:id": "3607937", 
        "ne:FeatureCla": "Admin-0 countries", 
        "ne:ADM0_DIF": 0.0, 
        "alias_DUT_Q": [
          "Maleisi\u00eb"
        ], 
        "alias_DUT_S": [
          "Maleisie"
        ], 
        "ne:ABBREV": "Malay.", 
        "alias_CZE_Q": [
          "Malajsie"
        ], 
        "alias_FIN_Q": [
          "Malesiasta"
        ], 
        "ne:GEOUNIT": "Malaysia", 
        "fullname": "Malaysia", 
        "ne:NAME": "Malaysia", 
        "lang": "ENG", 
        "name": "Malaysia", 
        "ne:TYPE": "Sovereign country", 
        "parent_woeid": 1, 
        "alias_UNK_Q": [
          "Malas\u00eda"
        ], 
        "alias_HUN_Q": [
          "Malajzia"
        ], 
        "alias_HUN_V": [
          "Mal\u00e1jf\u00f6ld"
        ], 
        "ne:NAME_SORT": "Malaysia", 
        "longitude": 114.402, 
        "ne:POP_EST": 25715819.0, 
        "ne_longitude": 119.18190392463995, 
        "iso": "MY", 
        "sw_latitude": 0.773131415200993, 
        "ne:GEOU_DIF": 0.0, 
        "ne:SOVEREIGNT": "Malaysia", 
        "ne:SU_DIF": 0.0, 
        "alias_FRE_Q": [
          "Malaisie"
        ]
      }, 
      "bbox": [
        100.08575687052709, 
        0.773131415200993, 
        119.18190392463995, 
        6.928052883324568
      ]
    }
  ]
}