{
  "type": "FeatureCollection", 
  "features": [
    {
      "geometry": {
        "type": "Polygon", 
        "coordinates": [
          [
            [
              144.80850427256973, 
              13.445614522242025
            ], 
            [
              144.7836479092033, 
              13.420293070890864
            ], 
            [
              144.76948856678786, 
              13.378977762707166
            ], 
            [
              144.76034183762033, 
              13.285520935081266
            ], 
            [
              144.73600223818175, 
              13.248959859530657
            ], 
            [
              144.71822554557332, 
              13.241621806358978
            ], 
            [
              144.69771000189894, 
              13.240794983175007
            ], 
            [
              144.68086348525992, 
              13.246582743663751
            ], 
            [
              144.67068322823678, 
              13.264643656207681
            ], 
            [
              144.6570923265918, 
              13.281851908945114
            ], 
            [
              144.65383671069856, 
              13.286812846249887
            ], 
            [
              144.64773889185312, 
              13.324665832969217
            ], 
            [
              144.6444832768592, 
              13.331487122212977
            ], 
            [
              144.63988407475364, 
              13.337300720223709
            ], 
            [
              144.63394128463693, 
              13.341951599171708
            ], 
            [
              144.6266549074084, 
              13.34512969980122
            ], 
            [
              144.63693851811638, 
              13.355258280881287
            ], 
            [
              144.64339807216112, 
              13.365516052268887
            ], 
            [
              144.6467570399405, 
              13.37830596915127
            ], 
            [
              144.64773889185312, 
              13.396056824237789
            ], 
            [
              144.64572351118545, 
              13.404299214957703
            ], 
            [
              144.6408142498238, 
              13.41460866318765
            ], 
            [
              144.6350781661775, 
              13.423367818734746
            ], 
            [
              144.6245361739551, 
              13.431067607105561
            ], 
            [
              144.62898034733206, 
              13.438560689905216
            ], 
            [
              144.63673181164603, 
              13.44297902486089
            ], 
            [
              144.64096927945172, 
              13.437656352356996
            ], 
            [
              144.65471521072482, 
              13.438999939468687
            ], 
            [
              144.71527998893623, 
              13.473261413516923
            ], 
            [
              144.7291292729949, 
              13.485431213685956
            ], 
            [
              144.7836479092033, 
              13.516462911161426
            ], 
            [
              144.79444828293998, 
              13.526901550598268
            ], 
            [
              144.80354333526486, 
              13.538916321139226
            ], 
            [
              144.81139815326384, 
              13.553411560332606
            ], 
            [
              144.83237878492292, 
              13.62048756943095
            ], 
            [
              144.83899336769616, 
              13.632502339971907
            ], 
            [
              144.85077559424474, 
              13.64350942017903
            ], 
            [
              144.86679528859923, 
              13.65288869243949
            ], 
            [
              144.88095463101456, 
              13.653922221194506
            ], 
            [
              144.88674239150333, 
              13.639995422771477
            ], 
            [
              144.89692264852647, 
              13.617826232729271
            ], 
            [
              144.91449263556376, 
              13.605243021418033
            ], 
            [
              144.93469812088148, 
              13.599661967399811
            ], 
            [
              144.9522681079187, 
              13.59842173307355
            ], 
            [
              144.95257816627543, 
              13.58666534404692
            ], 
            [
              144.9378503830897, 
              13.56036204078309
            ], 
            [
              144.90715458239208, 
              13.516462911161426
            ], 
            [
              144.87216963704623, 
              13.485017802543652
            ], 
            [
              144.80850427256973, 
              13.445614522242025
            ]
          ]
        ]
      }, 
      "type": "Feature", 
      "properties": {
        "alias_ENG_V": [
          "Guamanian"
        ], 
        "alias_KOR_Q": [
          "\uad0c"
        ], 
        "ne:LEVEL": 2.0, 
        "hierarchy": [
          "woe:country=23424832", 
          "woe:planet=1"
        ], 
        "ne_latitude": 13.653922221194506, 
        "ne_longitude": 144.95257816627543, 
        "placetype": "country", 
        "alias_KOR_V": [
          "\uad0c\uc12c"
        ], 
        "ne:ne_10m_adm": "GUM", 
        "alias_ENG_A": [
          "GU"
        ], 
        "ne:SUBUNIT": "Guam", 
        "ne:ADM0_A3": "GUM", 
        "ne:ScaleRank": 3, 
        "alias_CHI_Q": [
          "\u95dc\u5cf6"
        ], 
        "ne:GDP_MD_EST": 2500.0, 
        "ne:NAME": "Guam", 
        "alias_CHI_V": [
          "\u5173\u5c9b"
        ], 
        "alias_JPN_Q": [
          "\u30b0\u30a2\u30e0"
        ], 
        "alias_JPN_V": [
          "\u30b0\u30a2\u30e0\u5cf6"
        ], 
        "ne:FIPS_10_": 0.0, 
        "ne:TERR_": "U.S.A.", 
        "sw_longitude": 144.6245361739551, 
        "ne:NAME_FORMA": "Territory of Guam", 
        "ne:GEOUNIT": "Guam", 
        "provider": "geoplanet 7.6.0", 
        "latitude": 13.446, 
        "woe:id": 23424832, 
        "ne:OID_": 62, 
        "ne:ISO_A3": "GUM", 
        "ne:ISO_A2": "GU", 
        "date_indexed": "2010-12-02T18:21:30Z", 
        "ne:SOV_A3": "US1", 
        "fullname": "Guam", 
        "ne:GU_A3": "GUM", 
        "ne:MAP_COLOR": 1.0, 
        "ne:ADMIN": "Guam", 
        "ne:SU_A3": "GUM", 
        "ne:LabelRank": 8, 
        "ne:FeatureCla": "Adm-0 country", 
        "ne:ADM0_DIF": 1.0, 
        "ne:ABBREV": "Guam", 
        "alias_DUT_V": [
          "Goeam"
        ], 
        "ne:ISO_N3": 316.0, 
        "lang": "ENG", 
        "name": "Guam", 
        "ne:TYPE": "Dependency", 
        "ne:SU_DIF": 0.0, 
        "ne:POSTAL": "GU", 
        "ne:NAME_SORT": "Guam", 
        "longitude": 144.787, 
        "ne:POP_EST": 178430.0, 
        "iso": "GU", 
        "sw_latitude": 13.240794983175007, 
        "ne:GEOU_DIF": 0.0, 
        "ne:SOVEREIGNT": "United States of America"
      }, 
      "id": 23424832
    }
  ], 
  "bbox": [
    144.6245361739551, 
    13.240794983175007, 
    144.95257816627543, 
    13.653922221194506
  ]
}